MANIFEST.in
README.rst
setup.py
django_icons_icojoy_pointers.egg-info/PKG-INFO
django_icons_icojoy_pointers.egg-info/SOURCES.txt
django_icons_icojoy_pointers.egg-info/dependency_links.txt
django_icons_icojoy_pointers.egg-info/requires.txt
django_icons_icojoy_pointers.egg-info/top_level.txt
icons_icojoy_pointers/__init__.py
icons_icojoy_pointers/models.py
icons_icojoy_pointers/static/icons/.noremove
icons_icojoy_pointers/static/icons/icojoy-pointers/preview.jpg
icons_icojoy_pointers/static/icons/icojoy-pointers/readme.txt
icons_icojoy_pointers/static/icons/icojoy-pointers/PNG/001.png
icons_icojoy_pointers/static/icons/icojoy-pointers/PNG/002.png
icons_icojoy_pointers/static/icons/icojoy-pointers/PNG/003.png
icons_icojoy_pointers/static/icons/icojoy-pointers/PNG/004.png
icons_icojoy_pointers/static/icons/icojoy-pointers/PNG/005.png
icons_icojoy_pointers/static/icons/icojoy-pointers/PNG/006.png
icons_icojoy_pointers/static/icons/icojoy-pointers/PNG/007.png
icons_icojoy_pointers/static/icons/icojoy-pointers/PNG/008.png
icons_icojoy_pointers/static/icons/icojoy-pointers/PNG/009.png
icons_icojoy_pointers/static/icons/icojoy-pointers/PNG/010.png
icons_icojoy_pointers/static/icons/icojoy-pointers/PNG/011.png
icons_icojoy_pointers/static/icons/icojoy-pointers/PNG/012.png
icons_icojoy_pointers/static/icons/icojoy-pointers/PNG/013.png
icons_icojoy_pointers/static/icons/icojoy-pointers/PNG/014.png
icons_icojoy_pointers/static/icons/icojoy-pointers/PNG/015.png
icons_icojoy_pointers/static/icons/icojoy-pointers/PNG/016.png
icons_icojoy_pointers/static/icons/icojoy-pointers/PNG/017.png
icons_icojoy_pointers/static/icons/icojoy-pointers/PNG/018.png
icons_icojoy_pointers/static/icons/icojoy-pointers/PNG/019.png
icons_icojoy_pointers/static/icons/icojoy-pointers/PNG/020.png
icons_icojoy_pointers/static/icons/icojoy-pointers/PNG/021.png
icons_icojoy_pointers/static/icons/icojoy-pointers/PNG/022.png
icons_icojoy_pointers/static/icons/icojoy-pointers/PNG/023.png
icons_icojoy_pointers/static/icons/icojoy-pointers/PNG/024.png
icons_icojoy_pointers/static/icons/icojoy-pointers/PNG/025.png
icons_icojoy_pointers/static/icons/icojoy-pointers/PNG/026.png
icons_icojoy_pointers/static/icons/icojoy-pointers/PNG/027.png
